{
  "delegation": {
    "name": "سيدي بوزيد الغربية",
    "code": "51"
  },
  "circonscription": {
    "name": "سيدي بوزيد",
    "code": "430"
  },
  "bureau_vote": {
    "name": "ALL",
    "code": "9999"
  },
  "centre_vote": {
    "name": "م إبتدائية شارع الجمهوررية - النور",
    "code": "026"
  },
  "resultat": {
    "listes": [
      {
        "id": 464,
        "num": 36,
        "pourcentage": 26.136363636363637,
        "vote": 506,
        "name": "قائمة حركة النهضة"
      },
      {
        "id": 500,
        "num": 47,
        "pourcentage": 25.981404958677683,
        "vote": 503,
        "name": "قائمة العريضة الشعبية للحرية والعدالة والتنمية"
      },
      {
        "id": 446,
        "num": 24,
        "pourcentage": 4.855371900826446,
        "vote": 94,
        "name": "قائمة حزب المؤتمر من أجل الجمهورية"
      },
      {
        "id": 437,
        "num": 7,
        "pourcentage": 4.803719008264463,
        "vote": 93,
        "name": "قائمة حزب العمال الشيوعي التونسي (البديل الثوري)"
      },
      {
        "id": 286,
        "num": 30,
        "pourcentage": 3.977272727272727,
        "vote": 77,
        "name": "قائمة المستقل"
      },
      {
        "id": 377,
        "num": 34,
        "pourcentage": 3.254132231404959,
        "vote": 63,
        "name": "قائمة حركة البعث"
      },
      {
        "id": 137,
        "num": 61,
        "pourcentage": 2.272727272727273,
        "vote": 44,
        "name": "قائمة الحزب الديمقراطي التقدمي"
      },
      {
        "id": 447,
        "num": 16,
        "pourcentage": 2.2210743801652892,
        "vote": 43,
        "name": "قائمة حزب المبادرة"
      },
      {
        "id": 430,
        "num": 35,
        "pourcentage": 1.756198347107438,
        "vote": 34,
        "name": "قائمة حزب التكتل الديمقراطي من أجل العمل والحريات"
      },
      {
        "id": 96,
        "num": 20,
        "pourcentage": 1.6012396694214874,
        "vote": 31,
        "name": "قائمة الاتحاد الوطني الحر"
      },
      {
        "id": 394,
        "num": 19,
        "pourcentage": 1.4979338842975207,
        "vote": 29,
        "name": "قائمة حركة الوطنيون الديمقراطيون"
      },
      {
        "id": 259,
        "num": 45,
        "pourcentage": 1.4979338842975207,
        "vote": 29,
        "name": "قائمة القطب الديمقراطي الحداثي"
      },
      {
        "id": 387,
        "num": 52,
        "pourcentage": 1.2396694214876034,
        "vote": 24,
        "name": "قائمة حركة الشعب الوحدوية التقدمية"
      },
      {
        "id": 438,
        "num": 56,
        "pourcentage": 1.2396694214876034,
        "vote": 24,
        "name": "قائمة حزب العمل التونسي"
      },
      {
        "id": 382,
        "num": 14,
        "pourcentage": 1.18801652892562,
        "vote": 23,
        "name": "قائمة حركة الديمقراطيين الاشتراكيين"
      },
      {
        "id": 15,
        "num": 13,
        "pourcentage": 1.0330578512396695,
        "vote": 20,
        "name": "القائمة المستقلة للوطنيين الأحرار"
      },
      {
        "id": 338,
        "num": 2,
        "pourcentage": 0.9297520661157025,
        "vote": 18,
        "name": "قائمةالوحدة الشعبية"
      },
      {
        "id": 247,
        "num": 57,
        "pourcentage": 0.9297520661157025,
        "vote": 18,
        "name": "قائمة العمل والتضحية من أجل تونس"
      },
      {
        "id": 315,
        "num": 51,
        "pourcentage": 0.8264462809917356,
        "vote": 16,
        "name": "قائمة المناضلون الأحرار"
      },
      {
        "id": 386,
        "num": 59,
        "pourcentage": 0.8264462809917356,
        "vote": 16,
        "name": "قائمة حركة الشعب"
      },
      {
        "id": 347,
        "num": 5,
        "pourcentage": 0.7747933884297521,
        "vote": 15,
        "name": "قائمة الوعد الصادق"
      },
      {
        "id": 452,
        "num": 53,
        "pourcentage": 0.6714876033057852,
        "vote": 13,
        "name": "\"قائمة حزب المستقبل \"\"بلادي\"\"\""
      },
      {
        "id": 465,
        "num": 18,
        "pourcentage": 0.6714876033057852,
        "vote": 13,
        "name": "قائمة حزب تونس الخضراء"
      },
      {
        "id": 471,
        "num": 15,
        "pourcentage": 0.6198347107438017,
        "vote": 12,
        "name": "قائمة حماة سبعة عشرة ديسمبر"
      },
      {
        "id": 351,
        "num": 44,
        "pourcentage": 0.6198347107438017,
        "vote": 12,
        "name": "قائمة الوفاء لشهداء سيدي بوزيد"
      },
      {
        "id": 249,
        "num": 3,
        "pourcentage": 0.6198347107438017,
        "vote": 12,
        "name": "قائمة الغد"
      },
      {
        "id": 383,
        "num": 50,
        "pourcentage": 0.6198347107438017,
        "vote": 12,
        "name": "قائمة حركة الديمقراطيين الاشتراكيين (المؤتمر التاسع)"
      },
      {
        "id": 401,
        "num": 23,
        "pourcentage": 0.5165289256198348,
        "vote": 10,
        "name": "قائمة حزب آفاق تونس"
      },
      {
        "id": 339,
        "num": 37,
        "pourcentage": 0.46487603305785125,
        "vote": 9,
        "name": "قائمة الوحدة الوطنية"
      },
      {
        "id": 359,
        "num": 27,
        "pourcentage": 0.4132231404958678,
        "vote": 8,
        "name": "قائمة الوفاق الجمهوري"
      },
      {
        "id": 426,
        "num": 22,
        "pourcentage": 0.3615702479338843,
        "vote": 7,
        "name": "قائمة حزب التحالف الوطني للسلم والنماء"
      },
      {
        "id": 440,
        "num": 11,
        "pourcentage": 0.3615702479338843,
        "vote": 7,
        "name": "قائمة حزب الكرامة من أجل العدالة والتنمية"
      },
      {
        "id": 365,
        "num": 26,
        "pourcentage": 0.3615702479338843,
        "vote": 7,
        "name": "قائمة اليقين"
      },
      {
        "id": 458,
        "num": 1,
        "pourcentage": 0.30991735537190085,
        "vote": 6,
        "name": "قائمة حزب الوفاء لتونس"
      },
      {
        "id": 232,
        "num": 62,
        "pourcentage": 0.30991735537190085,
        "vote": 6,
        "name": "قائمة العدالة"
      },
      {
        "id": 21,
        "num": 28,
        "pourcentage": 0.30991735537190085,
        "vote": 6,
        "name": "قائمة 17ديسمبر للحرية والتنمية "
      },
      {
        "id": 296,
        "num": 60,
        "pourcentage": 0.2582644628099174,
        "vote": 5,
        "name": "قائمة المستقلة من أجل الكادحين"
      },
      {
        "id": 7,
        "num": 46,
        "pourcentage": 0.2582644628099174,
        "vote": 5,
        "name": "القائمة المستقلة الاتحاد"
      },
      {
        "id": 444,
        "num": 17,
        "pourcentage": 0.2582644628099174,
        "vote": 5,
        "name": "قائمة الحزب الليبرالي المغاربي"
      },
      {
        "id": 322,
        "num": 39,
        "pourcentage": 0.2582644628099174,
        "vote": 5,
        "name": "قائمة الميزان"
      },
      {
        "id": 392,
        "num": 38,
        "pourcentage": 0.2582644628099174,
        "vote": 5,
        "name": "قائمة حركة الوحدة الشعبية"
      },
      {
        "id": 556,
        "num": 42,
        "pourcentage": 0.2066115702479339,
        "vote": 4,
        "name": "قائمة مصير الأحرار"
      },
      {
        "id": 29,
        "num": 58,
        "pourcentage": 0.2066115702479339,
        "vote": 4,
        "name": "قائمة أحرار سيدي بوزيد"
      },
      {
        "id": 133,
        "num": 63,
        "pourcentage": 0.2066115702479339,
        "vote": 4,
        "name": "قائمة الحزب الإصلاحي الدستوري"
      },
      {
        "id": 376,
        "num": 33,
        "pourcentage": 0.2066115702479339,
        "vote": 4,
        "name": "قائمة حركة الإصلاح و العدالة الاجتماعية"
      },
      {
        "id": 483,
        "num": 21,
        "pourcentage": 0.2066115702479339,
        "vote": 4,
        "name": "قائمة شباب البناء"
      },
      {
        "id": 223,
        "num": 55,
        "pourcentage": 0.15495867768595042,
        "vote": 3,
        "name": "قائمة التنمية والمواطنة"
      },
      {
        "id": 221,
        "num": 31,
        "pourcentage": 0.15495867768595042,
        "vote": 3,
        "name": "قائمة التنمية والعدالة حق الجميع"
      },
      {
        "id": 469,
        "num": 48,
        "pourcentage": 0.15495867768595042,
        "vote": 3,
        "name": "قائمة حقنا في بلادنا"
      },
      {
        "id": 43,
        "num": 32,
        "pourcentage": 0.10330578512396695,
        "vote": 2,
        "name": "قائمة إرادة الشعب"
      },
      {
        "id": 159,
        "num": 4,
        "pourcentage": 0.10330578512396695,
        "vote": 2,
        "name": "قائمة الديمقراطية الشعبية"
      },
      {
        "id": 85,
        "num": 12,
        "pourcentage": 0.10330578512396695,
        "vote": 2,
        "name": "قائمة الإتحاد الديمقراطي الوحدوي"
      },
      {
        "id": 371,
        "num": 43,
        "pourcentage": 0.10330578512396695,
        "vote": 2,
        "name": "قائمة ثورة النور للحرية والكرامة"
      },
      {
        "id": 485,
        "num": 25,
        "pourcentage": 0.10330578512396695,
        "vote": 2,
        "name": "قائمة شباب الثورة المدينة"
      },
      {
        "id": 425,
        "num": 40,
        "pourcentage": 0.10330578512396695,
        "vote": 2,
        "name": "قائمة حزب الخضر للتقدّم (الخضر)"
      },
      {
        "id": 508,
        "num": 64,
        "pourcentage": 0.10330578512396695,
        "vote": 2,
        "name": "قائمة طريق الحرية والمواطنة"
      },
      {
        "id": 81,
        "num": 9,
        "pourcentage": 0.05165289256198347,
        "vote": 1,
        "name": "قائمة الإصلاح والتنمية"
      },
      {
        "id": 124,
        "num": 41,
        "pourcentage": 0.05165289256198347,
        "vote": 1,
        "name": "قائمة الحركة الإصلاحية التونسية"
      },
      {
        "id": 42,
        "num": 29,
        "pourcentage": 0.05165289256198347,
        "vote": 1,
        "name": "قائمة إرادة الحياة"
      },
      {
        "id": 49,
        "num": 49,
        "pourcentage": 0.05165289256198347,
        "vote": 1,
        "name": "قائمة ائتلاف الأمة"
      },
      {
        "id": 494,
        "num": 6,
        "pourcentage": 0.05165289256198347,
        "vote": 1,
        "name": "قائمة شباب سيدي بوزيد"
      },
      {
        "id": 57,
        "num": 10,
        "pourcentage": 0.05165289256198347,
        "vote": 1,
        "name": "قائمة الأحرار"
      },
      {
        "id": 219,
        "num": 54,
        "pourcentage": 0.05165289256198347,
        "vote": 1,
        "name": " قائمة التنمية والحقوق المدنية"
      },
      {
        "id": 413,
        "num": 65,
        "pourcentage": 0.05165289256198347,
        "vote": 1,
        "name": "قائمة حزب الأمة الديمقراطي الاجتماعي"
      },
      {
        "id": 176,
        "num": 8,
        "pourcentage": 0,
        "vote": 0,
        "name": "قائمة الشباب الأحرار"
      }
    ],
    "electeurs": {
      "votant": 2025,
      "enregistre": 2398
    },
    "bulletins": {
      "endommage": 8,
      "dans_urne": 2025,
      "correct": 1936,
      "delivre": 2710,
      "non_utilise": 679,
      "blancs": 23,
      "annule": 64
    }
  }
}