{
  "delegation": {
    "name": "بنزرت الشمالية",
    "code": "51"
  },
  "circonscription": {
    "name": "بنزرت",
    "code": "170"
  },
  "bureau_vote": {
    "name": "قاعة 2",
    "code": "02"
  },
  "centre_vote": {
    "name": "م إبتدائية شارع الهادي شاكر بنزرت - حسن النوري",
    "code": "009"
  },
  "resultat": {
    "listes": [
      {
        "num": 42,
        "pourcentage": 46.0177001953125,
        "vote": 364,
        "name": "قائمة حركة النهضة"
      },
      {
        "num": 20,
        "pourcentage": 13.906447410583496,
        "vote": 110,
        "name": "قائمة حزب المؤتمر من أجل الجمهورية"
      },
      {
        "num": 46,
        "pourcentage": 9.2288236618042,
        "vote": 73,
        "name": "قائمة حزب التكتل الديمقراطي من أجل العمل والحريات"
      },
      {
        "num": 17,
        "pourcentage": 4.8040452003479,
        "vote": 38,
        "name": "قائمة الحزب الديمقراطي التقدمي"
      },
      {
        "num": 43,
        "pourcentage": 4.0455121994018555,
        "vote": 32,
        "name": "قائمة حزب آفاق تونس"
      },
      {
        "num": 32,
        "pourcentage": 2.654867172241211,
        "vote": 21,
        "name": "قائمة القطب الديمقراطي الحداثي"
      },
      {
        "num": 28,
        "pourcentage": 2.2756004333496094,
        "vote": 18,
        "name": "قائمة حركة الشعب"
      },
      {
        "num": 53,
        "pourcentage": 1.769911527633667,
        "vote": 14,
        "name": "قائمة حزب العمال الشيوعي التونسي (البديل الثوري)"
      },
      {
        "num": 3,
        "pourcentage": 1.3906446695327759,
        "vote": 11,
        "name": "قائمة الغد"
      },
      {
        "num": 18,
        "pourcentage": 1.264222502708435,
        "vote": 10,
        "name": "قائمة العريضة الشعبية للحرية والعدالة والتنمية"
      },
      {
        "num": 2,
        "pourcentage": 1.1378002166748047,
        "vote": 9,
        "name": "قائمة الائتلاف الديمقراطي المستقل طريق السلامة"
      },
      {
        "num": 13,
        "pourcentage": 0.8849557638168335,
        "vote": 7,
        "name": "قائمة الاتحاد الوطني الحر"
      },
      {
        "num": 19,
        "pourcentage": 0.8849557638168335,
        "vote": 7,
        "name": "القائمة المستقلة دستورنا"
      },
      {
        "num": 4,
        "pourcentage": 0.6321112513542175,
        "vote": 5,
        "name": "قائمة الجلاء"
      },
      {
        "num": 8,
        "pourcentage": 0.6321112513542175,
        "vote": 5,
        "name": "قائمة حزب التحالف من أجل تونس"
      },
      {
        "num": 37,
        "pourcentage": 0.6321112513542175,
        "vote": 5,
        "name": "قائمة المستقل"
      },
      {
        "num": 40,
        "pourcentage": 0.6321112513542175,
        "vote": 5,
        "name": "قائمة بنزرت الأم"
      },
      {
        "num": 27,
        "pourcentage": 0.5056890249252319,
        "vote": 4,
        "name": "قائمة الإصلاح والتنمية"
      },
      {
        "num": 35,
        "pourcentage": 0.5056890249252319,
        "vote": 4,
        "name": "قائمة الحزب الليبرالي المغاربي"
      },
      {
        "num": 6,
        "pourcentage": 0.37926673889160156,
        "vote": 3,
        "name": "قائمة حركة الوحدويين الأحرار"
      },
      {
        "num": 9,
        "pourcentage": 0.37926673889160156,
        "vote": 3,
        "name": "قائمة الكرامة"
      },
      {
        "num": 15,
        "pourcentage": 0.37926673889160156,
        "vote": 3,
        "name": "قائمة جمعية بنزرت للانطلاق والتحدي"
      },
      {
        "num": 25,
        "pourcentage": 0.37926673889160156,
        "vote": 3,
        "name": "قائمة الوحدة الوطنية بنزرت"
      },
      {
        "num": 29,
        "pourcentage": 0.37926673889160156,
        "vote": 3,
        "name": "قائمة التآلف الجمهوري"
      },
      {
        "num": 44,
        "pourcentage": 0.37926673889160156,
        "vote": 3,
        "name": "قائمة الجبهة التقدمية الوطنية"
      },
      {
        "num": 45,
        "pourcentage": 0.37926673889160156,
        "vote": 3,
        "name": "قائمة الإتحاد الديمقراطي الوحدوي"
      },
      {
        "num": 7,
        "pourcentage": 0.25284451246261597,
        "vote": 2,
        "name": "قائمة الكرامة والحرية"
      },
      {
        "num": 11,
        "pourcentage": 0.25284451246261597,
        "vote": 2,
        "name": "قائمة الوفاء والصمود"
      },
      {
        "num": 21,
        "pourcentage": 0.25284451246261597,
        "vote": 2,
        "name": "قائمة التوازن والعدالة والمصالحة"
      },
      {
        "num": 22,
        "pourcentage": 0.25284451246261597,
        "vote": 2,
        "name": "قائمة من أجل جبهة وطنية تونسية"
      },
      {
        "num": 26,
        "pourcentage": 0.25284451246261597,
        "vote": 2,
        "name": "قائمة حزب الوفاق الجمهوري"
      },
      {
        "num": 31,
        "pourcentage": 0.25284451246261597,
        "vote": 2,
        "name": "القائمة المستقلة الوحدة الوطنية"
      },
      {
        "num": 38,
        "pourcentage": 0.25284451246261597,
        "vote": 2,
        "name": "القائمة المستقلة شغل حرية كرامة عدالة"
      },
      {
        "num": 39,
        "pourcentage": 0.25284451246261597,
        "vote": 2,
        "name": "قائمة من أجل التوازن بين الجهات"
      },
      {
        "num": 41,
        "pourcentage": 0.25284451246261597,
        "vote": 2,
        "name": "قائمة الإتحاد الشعبي الجمهوري"
      },
      {
        "num": 47,
        "pourcentage": 0.25284451246261597,
        "vote": 2,
        "name": "قائمة من أجل غد أفضل"
      },
      {
        "num": 49,
        "pourcentage": 0.25284451246261597,
        "vote": 2,
        "name": "قائمة حركة الديمقراطيين الاشتراكيين"
      },
      {
        "num": 1,
        "pourcentage": 0.12642225623130798,
        "vote": 1,
        "name": "قائمة الخضر"
      },
      {
        "num": 14,
        "pourcentage": 0.12642225623130798,
        "vote": 1,
        "name": "قائمة حزب الأمة الديمقراطي الاجتماعي"
      },
      {
        "num": 30,
        "pourcentage": 0.12642225623130798,
        "vote": 1,
        "name": "قائمة الطريق الثالث"
      },
      {
        "num": 34,
        "pourcentage": 0.12642225623130798,
        "vote": 1,
        "name": "قائمة المستقلون للشباب أصحاب الكفاءات والشهائد"
      },
      {
        "num": 36,
        "pourcentage": 0.12642225623130798,
        "vote": 1,
        "name": "قائمة العدل أساس العمران للعدل سنؤسس"
      },
      {
        "num": 54,
        "pourcentage": 0.12642225623130798,
        "vote": 1,
        "name": "قائمة حركة الشعب الوحدوية التقدمية"
      },
      {
        "num": 5,
        "pourcentage": 0,
        "vote": 0,
        "name": "قائمة الوفاء "
      },
      {
        "num": 10,
        "pourcentage": 0,
        "vote": 0,
        "name": "قائمة إئتلاف الأمة "
      },
      {
        "num": 12,
        "pourcentage": 0,
        "vote": 0,
        "name": "قائمة حزب الكرامة والعمل"
      },
      {
        "num": 16,
        "pourcentage": 0,
        "vote": 0,
        "name": "قائمة الحركة التقدمية التونسية (يزينا قهر ... يزينا حقرة)"
      },
      {
        "num": 23,
        "pourcentage": 0,
        "vote": 0,
        "name": "قائمة حركة الوحدة الشعبية"
      },
      {
        "num": 24,
        "pourcentage": 0,
        "vote": 0,
        "name": "قائمة إشكل"
      },
      {
        "num": 33,
        "pourcentage": 0,
        "vote": 0,
        "name": "قائمة الحوار"
      },
      {
        "num": 48,
        "pourcentage": 0,
        "vote": 0,
        "name": "قائمة النضال الإجتماعي"
      },
      {
        "num": 50,
        "pourcentage": 0,
        "vote": 0,
        "name": "قائمة البديل"
      },
      {
        "num": 51,
        "pourcentage": 0,
        "vote": 0,
        "name": "قائمة المنارة"
      },
      {
        "num": 52,
        "pourcentage": 0,
        "vote": 0,
        "name": "قائمة  العمل الديمقراطي الجمهوري"
      }
    ],
    "bulletins": {
      "endommage": 8,
      "dans_urne": 810,
      "correct": 791,
      "non_utilise": 182,
      "delivre": 1000,
      "blancs": 6,
      "annule": 13
    },
    "electeurs": {
      "votant": 810,
      "enregistre": 899
    }
  }
}