{
  "centres": [
    {
      "name": "م إبتدائية أريانة العليا",
      "code": "001"
    },
    {
      "name": "م إبتدائية الحبيب ثامر - اريانة المدينة",
      "code": "002"
    },
    {
      "name": "م إبتدائية المدرسة الدوليـة - اريانة المدينة",
      "code": "003"
    },
    {
      "name": "م إبتدائية المنزه الثامن - النصر 1",
      "code": "004"
    },
    {
      "name": "م إبتدائية المنزه الخامس 1شارع افريقيا",
      "code": "005"
    },
    {
      "name": "م إبتدائية المنزه السابع أريانة - النصر 1",
      "code": "006"
    },
    {
      "name": "م إبتدائية برج التركي - اريانة العليا",
      "code": "007"
    },
    {
      "name": "م إبتدائية حي التعمير 1 أريانة",
      "code": "008"
    },
    {
      "name": "م إبتدائية حي الفردوس أريانة - التعمير",
      "code": "009"
    },
    {
      "name": "م إبتدائية حي النور أريانة - التعمير",
      "code": "010"
    },
    {
      "name": "م إبتدائية رياض  النصر1 أريانة - النصر 2",
      "code": "011"
    },
    {
      "name": "م إبتدائية رياض الأندلس - أريانة العليا",
      "code": "012"
    },
    {
      "name": "م إبتدائية رياض النصر2",
      "code": "013"
    },
    {
      "name": "م إبتدائية سيدي الجبالي - اريانة المدينة",
      "code": "014"
    },
    {
      "name": "م إبتدائية شارع الحرية أريانة الجديدة",
      "code": "015"
    },
    {
      "name": "م إبتدائية طريق بنزرت أريانة - أريانة العليا",
      "code": "016"
    },
    {
      "name": "م إبتدائية فرحات حشاد أريانة - اريانة المدينة",
      "code": "017"
    },
    {
      "name": "م إبتدائية نهج بلال المنزه السادس",
      "code": "018"
    },
    {
      "name": "م.إعدادية  المنزه الخامس",
      "code": "019"
    },
    {
      "name": "م.إعدادية  المنزه السادس",
      "code": "020"
    },
    {
      "name": "م.إعدادية رياض النصــــــر أريانـة - النصر 2",
      "code": "021"
    },
    {
      "name": "معهد حي النصر - النصر 2",
      "code": "022"
    },
    {
      "name": "م إعدادية برج البكوش أريانة*",
      "code": "091"
    },
    {
      "name": "معهد المنزه السادس*",
      "code": "092"
    },
    {
      "name": "معهد  خير الدين أريانة*",
      "code": "093"
    }
  ]
}