{
  "centres": [
    {
      "name": "م إبتدائية  2مارس 34 الناظور",
      "code": "001"
    },
    {
      "name": "م إبتدائية الحناينية الناظور - عين البطوم",
      "code": "002"
    },
    {
      "name": "م إبتدائية الرقبة - صوغاس",
      "code": "003"
    },
    {
      "name": "م إبتدائية الزبيدين - صوار",
      "code": "004"
    },
    {
      "name": "م إبتدائية الشباعنة - بئر الشاوش",
      "code": "005"
    },
    {
      "name": "م إبتدائية الشعاليل - الناظور",
      "code": "006"
    },
    {
      "name": "م إبتدائية الضربانية - بئر الشاوش",
      "code": "007"
    },
    {
      "name": "م إبتدائية القايب العالي - عين البطوم",
      "code": "008"
    },
    {
      "name": "م إبتدائية المعيذر - بئر الشاوش",
      "code": "009"
    },
    {
      "name": "م إبتدائية الهنشير الجديد - الناظور",
      "code": "010"
    },
    {
      "name": "م إبتدائية بوعرارة الناظور - عين البطوم",
      "code": "011"
    },
    {
      "name": "م إبتدائية بئر الشاوش",
      "code": "012"
    },
    {
      "name": "م إبتدائية حي الجديد الناظور",
      "code": "013"
    },
    {
      "name": "م إبتدائية زواغة - الناظور",
      "code": "014"
    },
    {
      "name": "م إبتدائية سيدي بنور - صوار",
      "code": "015"
    },
    {
      "name": "م إبتدائية سيدي ناجي - بئر الشاوش",
      "code": "016"
    },
    {
      "name": "م إبتدائية صوار",
      "code": "017"
    },
    {
      "name": "م إبتدائية صوغاس الجنوبية",
      "code": "018"
    },
    {
      "name": "م إبتدائية صوغاس الشمالية",
      "code": "019"
    },
    {
      "name": "م إبتدائية عين البطوم",
      "code": "020"
    },
    {
      "name": "م إبتدائية عين جرس - صوغاس",
      "code": "021"
    },
    {
      "name": "م إعدادية ابن رشد بالناظور*",
      "code": "091"
    }
  ]
}