{
  "centres": [
    {
      "name": "م إبتدائية 14 جانفي أم العرائس - المحطة",
      "code": "001"
    },
    {
      "name": "م إبتدائية البركة أم العرائس - المحطة",
      "code": "002"
    },
    {
      "name": "م إبتدائية الحي العمالي ام العرائس - المحطة",
      "code": "003"
    },
    {
      "name": "م إبتدائية الدوارة ام العرائس",
      "code": "004"
    },
    {
      "name": "م إبتدائية الشنوفية أم العرائس",
      "code": "005"
    },
    {
      "name": "م إبتدائية العهد الجديد أم العرائس",
      "code": "006"
    },
    {
      "name": "م إبتدائية القطع أم العرائس",
      "code": "007"
    },
    {
      "name": "م إبتدائية الكدية أم العرائس - سيدي بو بكر",
      "code": "008"
    },
    {
      "name": "م إبتدائية الكسيلة ام العرائس",
      "code": "009"
    },
    {
      "name": "م إبتدائية اللوزة أم العرائس - الشنوفية",
      "code": "010"
    },
    {
      "name": "م إبتدائية المحطة ام العرائس",
      "code": "011"
    },
    {
      "name": "م إبتدائية المنجم ام العرائس - المحطة",
      "code": "012"
    },
    {
      "name": "م إبتدائية ام الاقصاب ام العرائس",
      "code": "013"
    },
    {
      "name": "م إبتدائية أولااد السّاعي - سيدي بو بكر",
      "code": "014"
    },
    {
      "name": "م إبتدائية بن عمار أم العرائس - السواطير",
      "code": "015"
    },
    {
      "name": "م إبتدائية حشانة ام العرائس",
      "code": "016"
    },
    {
      "name": "م إبتدائية حي الزهور أم العرائس - المحطة",
      "code": "017"
    },
    {
      "name": "م إبتدائية حي السوالمية أم العرائس - المحطة",
      "code": "018"
    },
    {
      "name": "م إبتدائية خالد ابن الوليد أم العرائس - سيدي بوبكر",
      "code": "019"
    },
    {
      "name": "م إبتدائية سيدي بوبكر ام العرائس",
      "code": "020"
    },
    {
      "name": "م إبتدائية طارق ابن زياد أم العرائس",
      "code": "021"
    },
    {
      "name": "م إبتدائية عقلة احمد ام العرائس - أم الأقصاب",
      "code": "022"
    },
    {
      "name": "م إبتدائية هنشير القلال أم العرائس - الدوارة",
      "code": "023"
    },
    {
      "name": "م إعدادية إبن منظور أم العرائس*",
      "code": "091"
    }
  ]
}