{
  "centres": [
    {
      "name": "م إبتدائية  الجريف القبلي",
      "code": "001"
    },
    {
      "name": "م إبتدائية ابن سينا جندوبة - الزغادية",
      "code": "002"
    },
    {
      "name": "م إبتدائية ابو القاسم الشابي جندوبة - الزغادية",
      "code": "003"
    },
    {
      "name": "م إبتدائية التطور",
      "code": "004"
    },
    {
      "name": "م إبتدائية الحدائق جندوبة - النور",
      "code": "005"
    },
    {
      "name": "م إبتدائية الرشاد جندوبة - التطور",
      "code": "006"
    },
    {
      "name": "م إبتدائية الزغادية",
      "code": "007"
    },
    {
      "name": "م إبتدائية السعادة",
      "code": "008"
    },
    {
      "name": "م إبتدائية الطرايدية - العيثه",
      "code": "009"
    },
    {
      "name": "م إبتدائية العزيمة سوق السبت",
      "code": "010"
    },
    {
      "name": "م إبتدائية العيثه",
      "code": "011"
    },
    {
      "name": "م إبتدائية الغراغيز - العيثه",
      "code": "012"
    },
    {
      "name": "م إبتدائية الفائز - جندوبة",
      "code": "013"
    },
    {
      "name": "م إبتدائية الفجر الجديد - الجريف القبلي",
      "code": "014"
    },
    {
      "name": "م إبتدائية الفوز - النور",
      "code": "015"
    },
    {
      "name": "م إبتدائية الملقى",
      "code": "016"
    },
    {
      "name": "م إبتدائية النور جندوبة",
      "code": "017"
    },
    {
      "name": "م إبتدائية بلحسن الدريسي - النور",
      "code": "018"
    },
    {
      "name": "م إبتدائية ساحة الشهداء جندوبة",
      "code": "019"
    },
    {
      "name": "م إبتدائية سوق السبت - العزيمة",
      "code": "020"
    },
    {
      "name": "م إبتدائية سيدي الهميسي - عين الكريمة",
      "code": "021"
    },
    {
      "name": "م إبتدائية شارع الطيب المهيري جندوبة",
      "code": "022"
    },
    {
      "name": "م إبتدائية شارع بورقيبة جندوبة",
      "code": "023"
    },
    {
      "name": "م إبتدائية عين الكريمة",
      "code": "024"
    },
    {
      "name": "م إبتدائية معلى",
      "code": "025"
    },
    {
      "name": "م إبتدائية ميتول - السعادة",
      "code": "026"
    },
    {
      "name": "م إبتدائية نهج ابن خلدون - جندوبة",
      "code": "027"
    },
    {
      "name": "معهد  9 افريل38   بجندوبة*",
      "code": "091"
    },
    {
      "name": "معهد  شارع الحرية بجندوبة*",
      "code": "092"
    },
    {
      "name": "م إعدادية مصطفى خريف بجندوبة*",
      "code": "093"
    }
  ]
}