{
  "centres": [
    {
      "name": "م إبتدائية  2مارس 34 الأخوات",
      "code": "001"
    },
    {
      "name": "م إبتدائية الأقصاب",
      "code": "002"
    },
    {
      "name": "م إبتدائية الخروبة - الاحواز الشمالية",
      "code": "003"
    },
    {
      "name": "م إبتدائية الطيب المهيري قعفور - قعفور الشرقية",
      "code": "004"
    },
    {
      "name": "م إبتدائية النويصر - الاحواز الشمالية",
      "code": "005"
    },
    {
      "name": "م إبتدائية الهوام - عين زريق",
      "code": "006"
    },
    {
      "name": "م إبتدائية بنورية قعفور - الأقصاب",
      "code": "007"
    },
    {
      "name": "م إبتدائية بورقيبة قعفور - قعفور الشرقية",
      "code": "008"
    },
    {
      "name": "م إبتدائية حي الزهور قعفور - قعفور الغربية",
      "code": "009"
    },
    {
      "name": "م إبتدائية شاكر قعفور - قعفور الشرقية",
      "code": "010"
    },
    {
      "name": "م إبتدائية عين زريق",
      "code": "011"
    },
    {
      "name": "م إبتدائية منجم الأخوات",
      "code": "012"
    },
    {
      "name": "م إبتدائية منزل نايل قعفور - عين زريق",
      "code": "013"
    },
    {
      "name": "م إعدادية التقنية بقعفور*",
      "code": "091"
    }
  ]
}